objathor/__init__.py
objathor/constants.py
objathor/main.py
objathor/annotation/__init__.py
objathor/annotation/annotation_utils.py
objathor/annotation/embed_synset_definitions.py
objathor/annotation/glb_to_annotation_pipeline.py
objathor/annotation/gpt_from_views.py
objathor/annotation/objaverse_annotations_utils.py
objathor/annotation/synset_from_description.py
objathor/asset_conversion/__init__.py
objathor/asset_conversion/asset_conversion_constants.py
objathor/asset_conversion/convert_obj_to_glb.py
objathor/asset_conversion/object_consolidater.py
objathor/asset_conversion/object_consolidater_blender.py
objathor/asset_conversion/object_consolidater_blender_package.py
objathor/asset_conversion/optimization_pipeline.py
objathor/asset_conversion/util.py
objathor/asset_conversion/colliders/__init__.py
objathor/asset_conversion/colliders/decompose_convex_obj.py
objathor/asset_conversion/colliders/generate_colliders.py
objathor/asset_conversion/data/empty_house.json
objathor/dataset/__init__.py
objathor/dataset/aggregate_asset_annotations.py
objathor/dataset/download_annotations.py
objathor/dataset/download_assets.py
objathor/dataset/download_features.py
objathor/dataset/download_holodeck_base_data.py
objathor/dataset/example.py
objathor/dataset/generate_holodeck_features.py
objathor/dataset/generate_thor_object_annotations.py
objathor/dataset/openai_batch_client.py
objathor/dataset/openai_batch_constants.py
objathor/dataset/openai_batch_server.py
objathor/dataset/postprocess_assets.py
objathor/dataset/upgrade_2023_holodeck_databases.py
objathor/dataset/upload_dataset.py
objathor/utils/__init__.py
objathor/utils/download_utils.py
objathor/utils/gpt_utils.py
objathor/utils/image_processing.py
objathor/utils/queries.py
objathor/utils/synsets.py
objathor/utils/types.py
objathor/utils/blender/__init__.py
objathor/utils/blender/render_glb.py
objathor-0.0.8.data/data/README.md
objathor-0.0.8.dist-info/LICENSE
objathor-0.0.8.dist-info/METADATA
objathor-0.0.8.dist-info/WHEEL
objathor-0.0.8.dist-info/top_level.txt
objathor-0.0.8.dist-info/RECORD
