Metadata-Version: 2.1
Name: objathor
Version: 0.0.8
Summary: Objaverse asset importer for THOR
Home-page: https://github.com/allenai/objathor
Author: Allen Institute for AI
Author-email: contact@allenai.org
License: Apache 2.0
Keywords: 3D assets,annotation,
Classifier: Development Status :: 4 - Beta
Classifier: Intended Audience :: Developers
Classifier: Topic :: Scientific/Engineering :: Artificial Intelligence
Classifier: License :: OSI Approved :: MIT License
Classifier: Programming Language :: Python :: 3.10
License-File: LICENSE
Requires-Dist: numpy>=1.23.5
Requires-Dist: tqdm>=4.66.1
Requires-Dist: compress-pickle>=2.1.0
Requires-Dist: filelock>=3.13.1
Requires-Dist: compress-json>=1.0.10
Requires-Dist: scikit-image>=0.21.0
Requires-Dist: objaverse>=0.1.7
Requires-Dist: trimesh>=4.0.1
Requires-Dist: msgpack>=1.0.7
Provides-Extra: annotation
Requires-Dist: openai>=1.3.8; extra == "annotation"
Requires-Dist: requests>=2.31.0; extra == "annotation"
Requires-Dist: prior>=1.0.3; extra == "annotation"
Requires-Dist: scikit-learn>=1.4.0; extra == "annotation"
Requires-Dist: APScheduler>=3.10.0; extra == "annotation"
Requires-Dist: gevent>=24.2.0; extra == "annotation"
